imgprocessor/__init__.py
imgprocessor/enums.py
imgprocessor/exceptions.py
imgprocessor/main.py
imgprocessor/processor.py
imgprocessor/utils.py
imgprocessor/parsers/__init__.py
imgprocessor/parsers/alpha.py
imgprocessor/parsers/base.py
imgprocessor/parsers/blur.py
imgprocessor/parsers/circle.py
imgprocessor/parsers/crop.py
imgprocessor/parsers/gray.py
imgprocessor/parsers/merge.py
imgprocessor/parsers/resize.py
imgprocessor/parsers/rotate.py
imgprocessor/parsers/watermark.py
py_img_processor-1.3.2.dist-info/LICENSE
py_img_processor-1.3.2.dist-info/METADATA
py_img_processor-1.3.2.dist-info/WHEEL
py_img_processor-1.3.2.dist-info/entry_points.txt
py_img_processor-1.3.2.dist-info/top_level.txt
py_img_processor-1.3.2.dist-info/RECORD
