Metadata-Version: 2.1
Name: py-img-processor
Version: 1.3.2
Summary: Image editor using Python and Pillow.
Home-page: https://github.com/SkylerHu/py-img-processor.git
Author: SkylerHu
Author-email: skylerhu@qq.com
License: MIT Licence
Keywords: image,img-processor,image-processor,imgprocessor,img-editor,image-editor
Platform: any
Classifier: Development Status :: 4 - Beta
Classifier: Intended Audience :: Developers
Classifier: License :: OSI Approved :: MIT License
Classifier: Programming Language :: Python :: 3
Classifier: Programming Language :: Python :: 3 :: Only
Classifier: Programming Language :: Python :: 3.9
Classifier: Programming Language :: Python :: 3.10
Classifier: Programming Language :: Python :: 3.11
Classifier: Programming Language :: Python :: 3.12
Classifier: Programming Language :: Python :: Implementation :: CPython
Requires-Python: >=3.9
License-File: LICENSE
Requires-Dist: py-enum >=2.1.1
Requires-Dist: Pillow >=8
